CHANGELOG.rst
LICENSE
MANIFEST.in
README.rst
VERSION
setup.py
src/pdfslash/__init__.py
src/pdfslash/slash.py
src/pdfslash.egg-info/PKG-INFO
src/pdfslash.egg-info/SOURCES.txt
src/pdfslash.egg-info/dependency_links.txt
src/pdfslash.egg-info/entry_points.txt
src/pdfslash.egg-info/not-zip-safe
src/pdfslash.egg-info/top_level.txt
tests/test_base.py
tests/test_img.py
tests/test_pdf.py
tests/test_scale.py