Metadata-Version: 2.1
Name: pdfslash
Version: 0.4.0
Summary: Crop pdf margins from interactive interpreter.
Home-page: https://github.com/openandclose/pdfslash
Author: Open Close
Author-email: openandclose23@gmail.com
License: MIT
Keywords: pdf crop trim MuPDF PyMuPDF briss
Classifier: Development Status :: 4 - Beta
Classifier: Intended Audience :: End Users/Desktop
Classifier: License :: OSI Approved :: MIT License
Classifier: Programming Language :: Python :: 3 :: Only
Classifier: Programming Language :: Python :: 3.6
Classifier: Programming Language :: Python :: 3.7
Classifier: Programming Language :: Python :: 3.8
Classifier: Programming Language :: Python :: 3.9
Classifier: Programming Language :: Python :: 3.10
Classifier: Topic :: Utilities
Requires-Python: ~=3.6
License-File: LICENSE
